{
  "week": 15,
  "days": [
    "// Montag",
    {
      "tagesteller": "Rindsgeschnetzeltes nach \"Stroganoff\", Kräuter-Kohlrabi und Goldzöpfli",
      "pasta-hit": "",
      "nachtessen": "Curry-Bratwurst mit Hagenbuttenketchup, und Gemüsereis"
    },
    "// Dienstag",
    {
      "tagesteller": "Schweinsragout mit Curry und Äpfeln, Kräutertomate und Brätlerkartoffeln\nDessert",
      "pasta-hit": "",
      "nachtessen": "Penne Carbonara (mit Speck, Zwiebeln und Petersilie an Rahmsauce)"
    },
    "// Mittwoch",
    {
      "tagesteller": "Poulet-Oberschenkel auf Tomatensauce, Broccoliröschen und Mandelreis",
      "pasta-hit": "",
      "nachtessen": "Rotes-Gemüsecurry mit Kichererbsen, Süsskartoffelburger mit schwarzem Sesam"
    },
    "// Donnerstag",
    {
      "tagesteller": "Schweinsbraten mit Rosmarinsauce, Ratatouillegemüse\nund Spiralen",
      "pasta-hit": "",
      "nachtessen": "Rösti-Pastetli mit Fleischfüllung, Erbsen, Karotten und Schwarzwurzeln"
    },
    "// Freitag",
    {
      "tagesteller": "Alaska-Seelachs filet mit Zitronenquarksauce, Rahmspinat und Salzkartoffeln",
      "pasta-hit": "",
      "nachtessen": "Älpler-Maccronen mit Apfelmus"
    },
    "// Samstag",
    {
      "tagesteller": "Kalbsragout mit Gemüse, Rotkabis und Eblysotto",
      "pasta-hit": "",
      "nachtessen": "Heisser Fleischkäse mit Kartoffel-Lauchgemüse"
    },
    "// Sonntag",
    {
      "tagesteller": "Schweinsschnitzel mit Pommery-Senf Sauce, Zucchetti und Kartoffelgratin",
      "pasta-hit": "",
      "nachtessen": "Tortelloni mit Bärlauchpesto und gerösteten Chashew-Nüssen"
    }
  ]
}
